quickopds/__init__.py
quickopds/style.xsl
quickopds-0.1.dist-info/METADATA
quickopds-0.1.dist-info/WHEEL
quickopds-0.1.dist-info/entry_points.txt
quickopds-0.1.dist-info/licenses/LICENSE
quickopds-0.1.dist-info/RECORD
