Metadata-Version: 2.4
Name: quickopds
Version: 0.1
Summary: Configuration-free script that statically creates an OPDS feed for a directory containing ebooks.
Project-URL: Homepage, https://github.com/mtorpey/quickopds
Project-URL: Issues, https://github.com/mtorpey/quickopds/issues
Author-email: Michael Young <mct25@st-andrews.ac.uk>
License-Expression: GPL-3.0
License-File: LICENSE
Classifier: Environment :: Console
Classifier: Operating System :: OS Independent
Classifier: Programming Language :: Python :: 3
Requires-Python: >=3.9
Requires-Dist: lxml~=6.0
Requires-Dist: pypdf~=6.0
